README.rst
setup.py
jeju/__init__.py
jeju/do.py
jeju.egg-info/PKG-INFO
jeju.egg-info/SOURCES.txt
jeju.egg-info/dependency_links.txt
jeju.egg-info/entry_points.txt
jeju.egg-info/requires.txt
jeju.egg-info/top_level.txt
jeju.egg-info/zip-safe
jeju/executor/__init__.py
jeju/executor/editor.py
jeju/executor/python.py
jeju/executor/shell.py
jeju/executor/yaml.py