Metadata-Version: 1.1
Name: jeju
Version: 0.3.0
Summary: Intelligent provisioning system based on specification documents
Home-page: https://github.com/pyengine/jeju
Author: Choonho Son
Author-email: choonho.son@gmail.com
License: BSD
Keywords: build configuration markdown
Platform: UNKNOWN
Classifier: Topic :: Utilities
Classifier: License :: OSI Approved :: BSD License
